[
  {
    "Employee Number": "00001",
    "Full Name": "KRISHNAN VAIDYANATHAN",
    "Work Email": "krishnan@finequs.com",
    "Password": "welcome@123"
  },
  {
    "Employee Number": "00003",
    "Full Name": "KAMARAJ ANBUKANI",
    "Work Email": "kamaraj@finequs.com",
    "Password": "welcome@123"
  },
  {
    "Employee Number": "00005",
    "Full Name": "Mohanasenthil S V",
    "Work Email": "mohanasenthil@finequs.com",
    "Password": "welcome@123"
  },
  {
    "Employee Number": "00006",
    "Full Name": "AMRISH KRISHNAN",
    "Work Email": "amrish@finequs.com",
    "Password": "welcome@123"
  },
  {
    "Employee Number": "00013",
    "Full Name": "ARAVINDAN K",
    "Work Email": "aravindan@finequs.com",
    "Password": "welcome@123"
  },
  {
    "Employee Number": "00021",
    "Full Name": "Balaji Settu",
    "Work Email": "bala@finequs.com",
    "Password": "welcome@123"
  },
  {
    "Employee Number": "00023",
    "Full Name": "Parthasarathi K",
    "Work Email": "parthasarathi@finequs.com",
    "Password": "welcome@123"
  },
  {
    "Employee Number": "00026",
    "Full Name": "Saranya K",
    "Work Email": "saranya@finequs.com",
    "Password": "welcome@123"
  },
  {
    "Employee Number": "00028",
    "Full Name": "SWATHY SUBRAMANIAN",
    "Work Email": "swathy@finequs.com",
    "Password": "welcome@123"
  },
  {
    "Employee Number": "00033",
    "Full Name": "Gobikannan R",
    "Work Email": "gobikannan@finequs.com",
    "Password": "welcome@123"
  },
  {
    "Employee Number": "00036",
    "Full Name": "Thonthiraju M",
    "Work Email": "thonthiraju@finequs.com",
    "Password": "welcome@123"
  },
  {
    "Employee Number": "00037",
    "Full Name": "Dhinesh Kumar S",
    "Work Email": "dhinesh@finequs.com",
    "Password": "welcome@123"
  },
  {
    "Employee Number": "00042",
    "Full Name": "Anbarasan s",
    "Work Email": "anbarasan@finequs.com",
    "Password": "welcome@123"
  },
  {
    "Employee Number": "00043",
    "Full Name": "Dhanabal Arumugam",
    "Work Email": "dhanabal@finequs.com",
    "Password": "welcome@123"
  },
  {
    "Employee Number": "00045",
    "Full Name": "V.X Prem",
    "Work Email": "prem@finequs.com",
    "Password": "welcome@123"
  },
  {
    "Employee Number": "00048",
    "Full Name": "Mande NAGA DURGA VARA Surekha",
    "Work Email": "surekha@finequs.com",
    "Password": "welcome@123"
  },
  {
    "Employee Number": "00051",
    "Full Name": "Vinoth Kumar D",
    "Work Email": "vinoth@finequs.com",
    "Password": "welcome@123"
  },
  {
    "Employee Number": "00059",
    "Full Name": "Sarathkumar Ayyappan",
    "Work Email": "sarathkumar@finequs.com",
    "Password": "welcome@123"
  },
  {
    "Employee Number": "00060",
    "Full Name": "Kingsly A",
    "Work Email": "kingsly@finequs.com",
    "Password": "welcome@123"
  },
  {
    "Employee Number": "00061",
    "Full Name": "Satheeshkumar N",
    "Work Email": "satheeshkumar.n@finequs.com",
    "Password": "welcome@123"
  },
  {
    "Employee Number": "00064",
    "Full Name": "Alina Kuruvila",
    "Work Email": "alina@finequs.com",
    "Password": "welcome@123"
  },
  {
    "Employee Number": "00066",
    "Full Name": "R Sathyanarayanan",
    "Work Email": "sathyanarayanan@finequs.com",
    "Password": "welcome@123"
  },
  {
    "Employee Number": "00070",
    "Full Name": "Suresh K",
    "Work Email": "suresh@finequs.com",
    "Password": "welcome@123"
  },
  {
    "Employee Number": "00071",
    "Full Name": "Rajasekar G",
    "Work Email": "raja.sekar@finequs.com",
    "Password": "welcome@123"
  },
  {
    "Employee Number": "00076",
    "Full Name": "ABBAS H",
    "Work Email": "abbas@finequs.com",
    "Password": "welcome@123"
  },
  {
    "Employee Number": "00078",
    "Full Name": "Mary Yollent J P",
    "Work Email": "mary@finequs.com",
    "Password": "welcome@123"
  },
  {
    "Employee Number": "00080",
    "Full Name": "Ramya E",
    "Work Email": "ramya.e@finequs.com",
    "Password": "welcome@123"
  },
  {
    "Employee Number": "00081",
    "Full Name": "Thabasum A",
    "Work Email": "thabasum.a@finequs.com",
    "Password": "welcome@123"
  },
  {
    "Employee Number": "00082",
    "Full Name": "Sabiya S",
    "Work Email": "sabiya.t@finequs.com",
    "Password": "welcome@123"
  },
  {
    "Employee Number": "00085",
    "Full Name": "Mohanraj M",
    "Work Email": "mohanrajmmcdc@gmail.com",
    "Password": "welcome@123"
  },
  {
    "Employee Number": "00086",
    "Full Name": "Indrabai L",
    "Work Email": "indrabai@finequs.com",
    "Password": "welcome@123"
  },
  {
    "Employee Number": "00087",
    "Full Name": "Sathya Subramaniyan",
    "Work Email": "sathya@finequs.com",
    "Password": "welcome@123"
  },
  {
    "Employee Number": "00088",
    "Full Name": "Alex Pandi S",
    "Work Email": "abc@gmail.com",
    "Password": "welcome@123"
  },
  {
    "Employee Number": "00089",
    "Full Name": "Elango M",
    "Work Email": "elango@finequs.com",
    "Password": "welcome@123"
  },
  {
    "Employee Number": "00091",
    "Full Name": "B Nirmal Kumar",
    "Work Email": "nirmal@finequs.com",
    "Password": "welcome@123"
  },
  {
    "Employee Number": "00092",
    "Full Name": "Mallela Rekha Meghana",
    "Work Email": "meghana@finequs.com",
    "Password": "welcome@123"
  },
  {
    "Employee Number": "00093",
    "Full Name": "George Veda Muthu",
    "Work Email": "george@finequs.com",
    "Password": "welcome@123"
  },
  {
    "Employee Number": "00098",
    "Full Name": "BOLLINENI BHARATH",
    "Work Email": "bollinenibharathmba@gmail.com",
    "Password": "welcome@123"
  },
  {
    "Employee Number": "00099",
    "Full Name": "Honest Raj Y",
    "Work Email": "honestraj@finequs.com",
    "Password": "welcome@123"
  },
  {
    "Employee Number": "00100",
    "Full Name": "Mariappan Nagendran",
    "Work Email": "nmariappan@finequs.com",
    "Password": "welcome@123"
  },
  {
    "Employee Number": "00101",
    "Full Name": "Vijayaram P",
    "Work Email": "vijayaram@finequs.com",
    "Password": "welcome@123"
  },
  {
    "Employee Number": "00102",
    "Full Name": "D Sarguru",
    "Work Email": "sarguru@finequs.com",
    "Password": "welcome@123"
  },
  {
    "Employee Number": "00105",
    "Full Name": "Saravanan Sathiyamoorthy",
    "Work Email": "saravanan@finequs.com",
    "Password": "welcome@123"
  },
  {
    "Employee Number": "00108",
    "Full Name": "M Kathirvel",
    "Work Email": "kathirvel@finequs.com",
    "Password": "welcome@123"
  },
  {
    "Employee Number": "00109",
    "Full Name": "Mani Narayanan",
    "Work Email": "mani@finequs.com",
    "Password": "welcome@123"
  },
  {
    "Employee Number": "00110",
    "Full Name": "Chanda Kumari R",
    "Work Email": "chandakumari@finequs.com",
    "Password": "welcome@123"
  },
  {
    "Employee Number": "00111",
    "Full Name": "K Rajesh",
    "Work Email": "rajesh@finequs.com",
    "Password": "welcome@123"
  },
  {
    "Employee Number": "00112",
    "Full Name": "Sonaimuthu Murugesan",
    "Work Email": "sonaimuthu@finequs.com",
    "Password": "welcome@123"
  },
  {
    "Employee Number": "00113",
    "Full Name": "T Mahalingam",
    "Work Email": "mahalingam@finequs.com",
    "Password": "welcome@123"
  },
  {
    "Employee Number": "00114",
    "Full Name": "V Veeramurugan",
    "Work Email": "veeramurugan@finequs.com",
    "Password": "welcome@123"
  },
  {
    "Employee Number": "00117",
    "Full Name": "Stephanraj Y",
    "Work Email": "stephanpdy@gmail.com",
    "Password": "welcome@123"
  },
  {
    "Employee Number": "00127",
    "Full Name": "Divya Anburaj",
    "Work Email": "divya@finequs.com",
    "Password": "welcome@123"
  },
  {
    "Employee Number": "00128",
    "Full Name": "Somnath M",
    "Work Email": "somnath@finequs.com",
    "Password": "welcome@123"
  },
  {
    "Employee Number": "00130",
    "Full Name": "Rajnish Kumar",
    "Work Email": "rajnish@finequs.com",
    "Password": "welcome@123"
  },
  {
    "Employee Number": "00131",
    "Full Name": "Prabu Pandi",
    "Work Email": "prabu@finequs.com",
    "Password": "welcome@123"
  },
  {
    "Employee Number": "00133",
    "Full Name": "Sriram Venkatraman",
    "Work Email": "sriram.@finequs.com",
    "Password": "welcome@123"
  },
  {
    "Employee Number": "00134",
    "Full Name": "Malavika D",
    "Work Email": "malavika@finequs.com",
    "Password": "welcome@123"
  },
  {
    "Employee Number": "00135",
    "Full Name": "Bikram Kumar",
    "Work Email": "bikram@finequs.com",
    "Password": "welcome@123"
  },
  {
    "Employee Number": "00136",
    "Full Name": "Gowri Nithiya V C",
    "Work Email": "gowri@finequs.com",
    "Password": "welcome@123"
  },
  {
    "Employee Number": "00137",
    "Full Name": "R Sankaranarayanan",
    "Work Email": "sankaranarayanan@finequs.com",
    "Password": "welcome@123"
  },
  {
    "Employee Number": "00138",
    "Full Name": "Mohammed Asif I",
    "Work Email": "asif@finequs.com",
    "Password": "welcome@123"
  },
  {
    "Employee Number": "00139",
    "Full Name": "Pooja Girmalappa Alagi",
    "Work Email": "pooja@finequs.com",
    "Password": "welcome@123"
  },
  {
    "Employee Number": "00140",
    "Full Name": "VISHNUPRIYA A",
    "Work Email": "vishnu@finequs.com",
    "Password": "welcome@123"
  },
  {
    "Employee Number": "00141",
    "Full Name": "Monisha D",
    "Work Email": "monisha@finequs.com",
    "Password": "welcome@123"
  }
]